opentelemetry/exporter/cloud_logging/__init__.py
opentelemetry/exporter/cloud_logging/environment_variables.py
opentelemetry/exporter/cloud_logging/version.py
opentelemetry_exporter_gcp_logging-1.9.0a0.dist-info/LICENSE
opentelemetry_exporter_gcp_logging-1.9.0a0.dist-info/METADATA
opentelemetry_exporter_gcp_logging-1.9.0a0.dist-info/WHEEL
opentelemetry_exporter_gcp_logging-1.9.0a0.dist-info/entry_points.txt
opentelemetry_exporter_gcp_logging-1.9.0a0.dist-info/top_level.txt
opentelemetry_exporter_gcp_logging-1.9.0a0.dist-info/RECORD
