Metadata-Version: 2.1
Name: opentelemetry-exporter-gcp-logging
Version: 1.9.0a0
Summary: Google Cloud Logging exporter for OpenTelemetry
Home-page: https://github.com/GoogleCloudPlatform/opentelemetry-operations-python/tree/main/opentelemetry-exporter-gcp-logging
Author: Google
Author-email: opentelemetry-pypi@google.com
License: Apache-2.0
Platform: any
Classifier: Development Status :: 4 - Beta
Classifier: Intended Audience :: Developers
Classifier: License :: OSI Approved :: Apache Software License
Classifier: Programming Language :: Python
Classifier: Programming Language :: Python :: 3
Classifier: Programming Language :: Python :: 3.7
Classifier: Programming Language :: Python :: 3.8
Classifier: Programming Language :: Python :: 3.9
Classifier: Programming Language :: Python :: 3.10
Classifier: Programming Language :: Python :: 3.11
Classifier: Programming Language :: Python :: 3.12
Requires-Python: >=3.7
License-File: LICENSE
Requires-Dist: google-cloud-logging~=3.0
Requires-Dist: opentelemetry-sdk~=1.0
Requires-Dist: opentelemetry-resourcedetector-gcp==1.*,>=1.5.0dev0
Provides-Extra: test
